fw_curation/__init__.py
fw_curation/config.py
fw_curation/curator.py
fw_curation/processes.py
fw_curation/reporters.py
fw_curation/utils.py
fw_curation/walker.py
fw_curation/testing/__init__.py
fw_curation/testing/hierarchy.py
fw_curation-1.0.2.dist-info/METADATA
fw_curation-1.0.2.dist-info/WHEEL
fw_curation-1.0.2.dist-info/licenses/LICENSE
fw_curation-1.0.2.dist-info/RECORD
