Metadata-Version: 2.4
Name: fw-curation
Version: 1.0.2
Summary: Flywheel Curation tools
Project-URL: Homepage, https://flywheel-io.gitlab.io/tools/lib/fw-curation
Project-URL: Repository, https://gitlab.com/flywheel-io/tools/lib/fw-curation.git
Project-URL: Documentation, https://flywheel-io.gitlab.io/tools/lib/fw-curation
Author-email: Flywheel <support@flywheel.io>
License-Expression: MIT
License-File: LICENSE
Classifier: Topic :: Scientific/Engineering :: Medical Science Apps.
Classifier: Topic :: Software Development :: Libraries :: Python Modules
Requires-Python: ~=3.10
Requires-Dist: flywheel-sdk>=21.0.0
Requires-Dist: fw-client>=2.1.4
Requires-Dist: pydantic-settings>=2.11.0
Requires-Dist: pydantic<3.0,>=2.12.3
Provides-Extra: sdk
Requires-Dist: flywheel-sdk>=21.0.0; extra == 'sdk'
